corclient-1.0.1.dist-info/licenses/LICENSE
corecli/__init__.py
corecli/_version.py
corecli/auth.py
corecli/cli.py
corecli/pkce.py
corecli/utils.py
corclient-1.0.1.dist-info/METADATA
corclient-1.0.1.dist-info/WHEEL
corclient-1.0.1.dist-info/entry_points.txt
corclient-1.0.1.dist-info/top_level.txt
corclient-1.0.1.dist-info/RECORD
