Metadata-Version: 2.4
Name: corclient
Version: 1.0.1
Summary: Internal CLI tool for microservices management, infrastructure administration and monitoring with AWS Cognito authentication
Author-email: Carlos Ferrer <cferrer@projectcor.com>
Maintainer-email: Carlos Ferrer <cferrer@projectcor.com>
License-Expression: MIT
Project-URL: Homepage, https://github.com/ProjectCORTeam/corcli
Project-URL: Documentation, https://github.com/ProjectCORTeam/corcli#readme
Project-URL: Repository, https://github.com/ProjectCORTeam/corcli.git
Project-URL: Bug Tracker, https://github.com/ProjectCORTeam/corcli/issues
Project-URL: Changelog, https://github.com/ProjectCORTeam/corcli/releases
Keywords: cli,microservices,infrastructure,devops,monitoring,aws,internal-tools
Classifier: Development Status :: 4 - Beta
Classifier: Intended Audience :: Developers
Classifier: Intended Audience :: System Administrators
Classifier: Intended Audience :: Information Technology
Classifier: Topic :: System :: Monitoring
Classifier: Topic :: System :: Systems Administration
Classifier: Topic :: Software Development :: Build Tools
Classifier: Topic :: Internet :: WWW/HTTP :: Dynamic Content
Classifier: Topic :: Utilities
Classifier: Programming Language :: Python :: 3
Classifier: Programming Language :: Python :: 3.9
Classifier: Programming Language :: Python :: 3.10
Classifier: Programming Language :: Python :: 3.11
Classifier: Programming Language :: Python :: 3.12
Classifier: Operating System :: OS Independent
Classifier: Environment :: Console
Classifier: Natural Language :: English
Requires-Python: >=3.9
License-File: LICENSE
Requires-Dist: typer>=0.12
Requires-Dist: rich>=13
Requires-Dist: flask>=2.3
Requires-Dist: requests>=2.31
Provides-Extra: dev
Requires-Dist: ruff>=0.1.0; extra == "dev"
Requires-Dist: black>=23.0.0; extra == "dev"
Requires-Dist: mypy>=1.0.0; extra == "dev"
Requires-Dist: pytest>=7.0.0; extra == "dev"
Requires-Dist: types-requests>=2.31.0; extra == "dev"
Dynamic: license-file
